{"state": "ES", "code": "3200102", "name": "Afonso Claudio"}
{"state": "ES", "code": "3200169", "name": "Agua Doce Do Norte"}
{"state": "ES", "code": "3200136", "name": "Aguia Branca"}
{"state": "ES", "code": "3200201", "name": "Alegre"}
{"state": "ES", "code": "3200300", "name": "Alfredo Chaves"}
{"state": "ES", "code": "3200359", "name": "Alto Rio Novo"}
{"state": "ES", "code": "3200409", "name": "Anchieta"}
{"state": "ES", "code": "3200508", "name": "Apiaca"}
{"state": "ES", "code": "3200607", "name": "Aracruz"}
{"state": "ES", "code": "3200706", "name": "Atilio Vivacqua"}
{"state": "ES", "code": "3200805", "name": "Baixo Guandu"}
{"state": "ES", "code": "3200904", "name": "Barra De Sao Francisco"}
{"state": "ES", "code": "3201001", "name": "Boa Esperanca"}
{"state": "ES", "code": "3201100", "name": "Bom Jesus Do Norte"}
{"state": "ES", "code": "3201159", "name": "Brejetuba"}
{"state": "ES", "code": "3201209", "name": "Cachoeiro De Itapemirim"}
{"state": "ES", "code": "3201308", "name": "Cariacica"}
{"state": "ES", "code": "3201407", "name": "Castelo"}
{"state": "ES", "code": "3201506", "name": "Colatina"}
{"state": "ES", "code": "3201605", "name": "Conceicao Da Barra"}
{"state": "ES", "code": "3201704", "name": "Conceicao Do Castelo"}
{"state": "ES", "code": "3201803", "name": "Divino De Sao Lourenco"}
{"state": "ES", "code": "3201902", "name": "Domingos Martins"}
{"state": "ES", "code": "3202009", "name": "Dores Do Rio Preto"}
{"state": "ES", "code": "3202108", "name": "Ecoporanga"}
{"state": "ES", "code": "3202207", "name": "Fundao"}
{"state": "ES", "code": "3202256", "name": "Governador Lindenberg"}
{"state": "ES", "code": "3202306", "name": "Guacui"}
{"state": "ES", "code": "3202405", "name": "Guarapari"}
{"state": "ES", "code": "3202454", "name": "Ibatiba"}
{"state": "ES", "code": "3202504", "name": "Ibiracu"}
{"state": "ES", "code": "3202553", "name": "Ibitirama"}
{"state": "ES", "code": "3202603", "name": "Iconha"}
{"state": "ES", "code": "3202652", "name": "Irupi"}
{"state": "ES", "code": "3202702", "name": "Itaguacu"}
{"state": "ES", "code": "3202801", "name": "Itapemirim"}
{"state": "ES", "code": "3202900", "name": "Itarana"}
{"state": "ES", "code": "3203007", "name": "Iuna"}
{"state": "ES", "code": "3203056", "name": "Jaguare"}
{"state": "ES", "code": "3203106", "name": "Jeronimo Monteiro"}
{"state": "ES", "code": "3203130", "name": "Joao Neiva"}
{"state": "ES", "code": "3203163", "name": "Laranja Da Terra"}
{"state": "ES", "code": "3203205", "name": "Linhares"}
{"state": "ES", "code": "3203304", "name": "Mantenopolis"}
{"state": "ES", "code": "3203320", "name": "Marataizes"}
{"state": "ES", "code": "3203346", "name": "Marechal Floriano"}
{"state": "ES", "code": "3203353", "name": "Marilandia"}
{"state": "ES", "code": "3203403", "name": "Mimoso Do Sul"}
{"state": "ES", "code": "3203502", "name": "Montanha"}
{"state": "ES", "code": "3203601", "name": "Mucurici"}
{"state": "ES", "code": "3203700", "name": "Muniz Freire"}
{"state": "ES", "code": "3203809", "name": "Muqui"}
{"state": "ES", "code": "3203908", "name": "Nova Venecia"}
{"state": "ES", "code": "3204005", "name": "Pancas"}
{"state": "ES", "code": "3204054", "name": "Pedro Canario"}
{"state": "ES", "code": "3204104", "name": "Pinheiros"}
{"state": "ES", "code": "3204203", "name": "Piuma"}
{"state": "ES", "code": "3204252", "name": "Ponto Belo"}
{"state": "ES", "code": "3204302", "name": "Presidente Kennedy"}
{"state": "ES", "code": "3204351", "name": "Rio Bananal"}
{"state": "ES", "code": "3204401", "name": "Rio Novo Do Sul"}
{"state": "ES", "code": "3204500", "name": "Santa Leopoldina"}
{"state": "ES", "code": "3204559", "name": "Santa Maria De Jetiba"}
{"state": "ES", "code": "3204609", "name": "Santa Teresa"}
{"state": "ES", "code": "3204658", "name": "Sao Domingos Do Norte"}
{"state": "ES", "code": "3204708", "name": "Sao Gabriel Da Palha"}
{"state": "ES", "code": "3204807", "name": "Sao Jose Do Calcado"}
{"state": "ES", "code": "3204906", "name": "Sao Mateus"}
{"state": "ES", "code": "3204955", "name": "Sao Roque Do Canaa"}
{"state": "ES", "code": "3205002", "name": "Serra"}
{"state": "ES", "code": "3205010", "name": "Sooretama"}
{"state": "ES", "code": "3205036", "name": "Vargem Alta"}
{"state": "ES", "code": "3205069", "name": "Venda Nova Do Imigrante"}
{"state": "ES", "code": "3205101", "name": "Viana"}
{"state": "ES", "code": "3205150", "name": "Vila Pavao"}
{"state": "ES", "code": "3205176", "name": "Vila Valerio"}
{"state": "ES", "code": "3205200", "name": "Vila Velha"}
{"state": "ES", "code": "3205309", "name": "Vitoria"}
